setup.py
gg/__init__.py
gg/consts.py
gg/gg.py
shit.egg-info/PKG-INFO
shit.egg-info/SOURCES.txt
shit.egg-info/dependency_links.txt
shit.egg-info/entry_points.txt
shit.egg-info/requires.txt
shit.egg-info/top_level.txt