Metadata-Version: 1.0
Name: shit
Version: 0.0.1
Summary: For Github Notifications
Home-page: https://github.com/MrKiven/gg/
Author: kiven
Author-email: kiven.mr@gmail.com
License: UNKNOWN
Platform: UNKNOWN
